RustGuanfangJiaochengZhongwenban/README.md
RustGuanfangJiaochengZhongwenban/__init__.py
RustGuanfangJiaochengZhongwenban/__main__.py
RustGuanfangJiaochengZhongwenban/file.epub
RustGuanfangJiaochengZhongwenban/index.html
RustGuanfangJiaochengZhongwenban/css/__init__.py
RustGuanfangJiaochengZhongwenban/css/annotations.css
RustGuanfangJiaochengZhongwenban/css/main.css
RustGuanfangJiaochengZhongwenban/css/normalize.css
RustGuanfangJiaochengZhongwenban/css/popup.css
RustGuanfangJiaochengZhongwenban/font/__init__.py
RustGuanfangJiaochengZhongwenban/font/fontello.eot
RustGuanfangJiaochengZhongwenban/font/fontello.svg
RustGuanfangJiaochengZhongwenban/font/fontello.ttf
RustGuanfangJiaochengZhongwenban/font/fontello.woff
RustGuanfangJiaochengZhongwenban/img/__init__.py
RustGuanfangJiaochengZhongwenban/img/annotator-glyph-sprite.png
RustGuanfangJiaochengZhongwenban/img/annotator-icon-sprite.png
RustGuanfangJiaochengZhongwenban/img/apple-touch-icon.png
RustGuanfangJiaochengZhongwenban/img/cancelfullscreen.png
RustGuanfangJiaochengZhongwenban/img/close.png
RustGuanfangJiaochengZhongwenban/img/fullscreen.png
RustGuanfangJiaochengZhongwenban/img/loader.gif
RustGuanfangJiaochengZhongwenban/img/menu-icon.png
RustGuanfangJiaochengZhongwenban/img/save.png
RustGuanfangJiaochengZhongwenban/img/saved.png
RustGuanfangJiaochengZhongwenban/img/settings-s.png
RustGuanfangJiaochengZhongwenban/img/settings.png
RustGuanfangJiaochengZhongwenban/img/star.png
RustGuanfangJiaochengZhongwenban/js/__init__.py
RustGuanfangJiaochengZhongwenban/js/epub.js
RustGuanfangJiaochengZhongwenban/js/epub.min.js
RustGuanfangJiaochengZhongwenban/js/epub.min.map
RustGuanfangJiaochengZhongwenban/js/hooks.min.js
RustGuanfangJiaochengZhongwenban/js/hooks.min.map
RustGuanfangJiaochengZhongwenban/js/reader.js
RustGuanfangJiaochengZhongwenban/js/reader.js.map
RustGuanfangJiaochengZhongwenban/js/reader.min.js
RustGuanfangJiaochengZhongwenban/js/reader.min.map
RustGuanfangJiaochengZhongwenban/js/hooks/__init__.py
rust_guanfang_jiaocheng_zhongwenban-2024.3.2.0.dist-info/METADATA
rust_guanfang_jiaocheng_zhongwenban-2024.3.2.0.dist-info/WHEEL
rust_guanfang_jiaocheng_zhongwenban-2024.3.2.0.dist-info/entry_points.txt
rust_guanfang_jiaocheng_zhongwenban-2024.3.2.0.dist-info/top_level.txt
rust_guanfang_jiaocheng_zhongwenban-2024.3.2.0.dist-info/RECORD
